yakari/__init__.py
yakari/app.css
yakari/app.py
yakari/cli.py
yakari/constants.py
yakari/rich_render.py
yakari/types.py
yakari/screens/__init__.py
yakari/screens/choice_argument.py
yakari/screens/menu.py
yakari/screens/results.py
yakari/screens/value_argument.py
yakari/widgets/__init__.py
yakari/widgets/argument_input.py
yakari/widgets/command_runner.py
yakari/widgets/footer.py
yakari/widgets/suggestions.py
yakari/widgets/tags.py
yakari-0.1.1.dist-info/METADATA
yakari-0.1.1.dist-info/WHEEL
yakari-0.1.1.dist-info/entry_points.txt
yakari-0.1.1.dist-info/RECORD
