Metadata-Version: 2.4
Name: yakari
Version: 0.1.1
Summary: Interactive command building tool.
Requires-Python: >=3.12
Requires-Dist: pydantic<3.0.0,>=2.9.2
Requires-Dist: rich<15.0.0,>=14.1.0
Requires-Dist: textual<6.0.0,>=5.3.0
Requires-Dist: tomlkit>=0.13.2
